stormcatchments/__init__.py
stormcatchments/constants.py
stormcatchments/delineate.py
stormcatchments/network.py
stormcatchments/terrain.py
stormcatchments/topology.py
stormcatchments-0.4.1.dist-info/LICENSE.txt
stormcatchments-0.4.1.dist-info/METADATA
stormcatchments-0.4.1.dist-info/WHEEL
stormcatchments-0.4.1.dist-info/top_level.txt
stormcatchments-0.4.1.dist-info/RECORD
