Metadata-Version: 2.1
Name: stormcatchments
Version: 0.4.1
Summary: Stormwater network aware catchment delineation
Home-page: https://github.com/t-ott/stormcatchments
Author: Thomas Ott
Author-email: tommy.ott617@gmail.com
License: GPLv3
Classifier: License :: OSI Approved :: GNU General Public License v3 (GPLv3)
Classifier: Programming Language :: Python :: 3
Classifier: Programming Language :: Python :: 3.8
Classifier: Programming Language :: Python :: 3.9
Classifier: Topic :: Scientific/Engineering :: GIS
Classifier: Topic :: Scientific/Engineering :: Hydrology
Requires-Python: >=3.8
License-File: LICENSE.txt
Requires-Dist: geopandas
Requires-Dist: networkx
Requires-Dist: pysheds
Requires-Dist: rtree
Provides-Extra: basemap
Requires-Dist: contextily ; extra == 'basemap'
Provides-Extra: dev
Requires-Dist: pytest ; extra == 'dev'
Provides-Extra: plotting
Requires-Dist: matplotlib ; extra == 'plotting'
